django_celery_beat_endpoint/__init__.py
django_celery_beat_endpoint/beat.py
django_celery_beat_endpoint/celery.py
django_celery_beat_endpoint/defaults.py
django_celery_beat_endpoint/backends/__init__.py
django_celery_beat_endpoint/backends/base.py
django_celery_beat_endpoint-0.1.2.dist-info/LICENSE
django_celery_beat_endpoint-0.1.2.dist-info/METADATA
django_celery_beat_endpoint-0.1.2.dist-info/WHEEL
django_celery_beat_endpoint-0.1.2.dist-info/top_level.txt
django_celery_beat_endpoint-0.1.2.dist-info/RECORD
