Metadata-Version: 2.1
Name: django-celery-beat-endpoint
Version: 0.1.2
Summary: A library that provides basic status and tasks endpoint for Django Celery Beat.
Home-page: https://github.com/ZhaoQi99/django-celery-beat-endpoint
Author: Qi Zhao
Author-email: zhaoqi99@outlook.com
Project-URL: Homepage, https://github.com/ZhaoQi99/django-celery-beat-endpoint
Project-URL: Changelog, https://github.com/ZhaoQi99/django-celery-beat-endpoint/releases
Project-URL: Source, https://github.com/ZhaoQi99/django-celery-beat-endpoint
Project-URL: Issue Tracker, https://github.com/ZhaoQi99/django-celery-beat-endpoint/issues
Keywords: django,celery,beat,status,endpoint
Classifier: License :: OSI Approved :: GNU General Public License v3 (GPLv3)
Classifier: Programming Language :: Python :: 3
Classifier: Programming Language :: Python :: 3.6
Classifier: Programming Language :: Python :: 3.7
Classifier: Programming Language :: Python :: 3.8
Classifier: Programming Language :: Python :: 3.9
Classifier: Programming Language :: Python :: 3.10
Classifier: Programming Language :: Python :: Implementation :: CPython
Requires-Python: >=3.6
License-File: LICENSE
Requires-Dist: celery
Requires-Dist: Django
